aiossdb/__init__.py
aiossdb/client.py
aiossdb/connection.py
aiossdb/errors.py
aiossdb/log.py
aiossdb/parser.py
aiossdb/pool.py
aiossdb/utils.py
aiossdb-0.0.5.dist-info/METADATA
aiossdb-0.0.5.dist-info/RECORD
aiossdb-0.0.5.dist-info/WHEEL
aiossdb-0.0.5.dist-info/top_level.txt
