Metadata-Version: 2.1
Name: aiossdb
Version: 0.0.5
Summary: aiossdb is a library for accessing a ssdb database from the asyncio
Home-page: UNKNOWN
Author: Kevin
Author-email: dgt_x@foxmail.com
License: MIT
Keywords: aiossdb
Platform: UNKNOWN
Classifier: Development Status :: 3 - Alpha
Classifier: Programming Language :: Python :: 3
Classifier: Programming Language :: Python :: 3.6
Classifier: Intended Audience :: Developers
Classifier: License :: OSI Approved :: MIT License
Classifier: Operating System :: OS Independent
Classifier: Topic :: Software Development :: Libraries :: Python Modules
Provides-Extra: tests
Provides-Extra: tests
Requires-Dist: pytest; extra == 'tests'
Requires-Dist: pytest-cov; extra == 'tests'
Requires-Dist: pytest-asyncio; extra == 'tests'
